LICENSE
Examples/phones.tomsk.gov.ru.yml
Examples/reestr.minvyaz.ru-class-54118.yml
Examples/reestr.minvyaz.ru.yml
tests/conftest.py
tests/test_grab.py
tests/test_utils.py
tests/test_webparser.py
xpathwebscrapper/__init__.py
xpathwebscrapper/__main__.py
xpathwebscrapper/grab.py
xpathwebscrapper/utils.py
xpathwebscrapper/webparser.py
xpathwebscrapper-0.2.dev16.dist-info/LICENSE
xpathwebscrapper-0.2.dev16.dist-info/METADATA
xpathwebscrapper-0.2.dev16.dist-info/WHEEL
xpathwebscrapper-0.2.dev16.dist-info/entry_points.txt
xpathwebscrapper-0.2.dev16.dist-info/top_level.txt
xpathwebscrapper-0.2.dev16.dist-info/zip-safe
xpathwebscrapper-0.2.dev16.dist-info/RECORD
